passlord/__init__.py
passlord/passlord.py
passlord/patterns/__init__.py
passlord/patterns/rules.txt
passlord-1.0.1.dist-info/LICENCE
passlord-1.0.1.dist-info/METADATA
passlord-1.0.1.dist-info/WHEEL
passlord-1.0.1.dist-info/entry_points.txt
passlord-1.0.1.dist-info/top_level.txt
passlord-1.0.1.dist-info/RECORD
