Metadata-Version: 2.1
Name: passlord
Version: 1.0.1
Summary: Passlord is a smart tool that creates lists of possible passwords using clever methods.
Home-page: https://github.com/navnee1h/passlord
Author: navnee1h
License: MIT
Classifier: Development Status :: 3 - Alpha
Classifier: Intended Audience :: Developers
Classifier: Intended Audience :: End Users/Desktop
Classifier: License :: OSI Approved :: MIT License
Classifier: Operating System :: POSIX :: Linux
Classifier: Programming Language :: Python :: 3
Classifier: Topic :: Security
Classifier: Topic :: Utilities
License-File: LICENCE
